{
    "baidu_accesstoken": "24.1433c9f37d02990dc735781a40156cbb.2592000.1735640798.282335-57504589",
    "zhipu_apikey": "09b661d1474234d67f789696d13be3d0.AAY0t9VYR1TFuHdg",
    "baidu_appbuliderkey":"",
    "gemini_apikey":"AIzaSyBMuRPHbFmFpNqXVw7Umwr1AfuB1zWatWA",
    "userservice":"47.121.138.76",
    "model":[
        {
            "name":"文心一言 4", 
            "des":"百度自研的旗舰级超大规模⼤语⾔模型，相较ERNIE 3.5实现了模型能力全面升级，广泛适用于各领域复杂任务场景；支持自动对接百度搜索插件，保障问答信息时效。 百度文心系列中效果最强大的⼤语⾔模型，理解、生成、逻辑、记忆能力达到业界顶尖水平。",
            "value":"completions_pro",
            "from":"ernie"
        },
        
        {
            "name":"文心一言3.5", 
            "des":"百度自研的旗舰级大规模⼤语⾔模型，覆盖海量中英文语料，具有强大的通用能力，可满足绝大部分对话问答、创作生成、插件应用场景要求；支持自动对接百度搜索插件，保障问答信息时效。",
            "value":"completions",
            "from":"ernie"
        },
        {
            "name":"文心一言Speed", 
            "des":"百度2024年最新发布的自研高性能大语言模型，通用能力优异，更好地处理特定场景问题，同时具备极佳的推理性。",
            "value":"ernie-speed-128k",
            "from":"ernie"
        },
        {
            "name":"文心一言Lite", 
            "des":"百度自研的轻量级大语言模型，兼顾优异的模型效果与推理性能，支持128K上下文长度。",
            "value":"ernie-lite-8k",
            "from":"ernie"
        },
        {
            "name":"GLM-4-flash", 
            "des":"智谱AI首个免费大模型API，兼具“高速度”和“经济性”两大特点，支持128K上下文。",
            "value":"glm-4-flash",
            "from":"zhipuai"
        },
        {
            "name":"GLM-4-air", 
            "des":"高性价比：推理能力和价格之间最平衡的模型，支持128K上下文。",
            "value":"glm-4-air",
            "from":"zhipuai"
        }
    ]
}